renkuaqs/__init__.py
renkuaqs/config.py
renkuaqs/graph_config.yaml
renkuaqs/graph_graphical_config.json
renkuaqs/graph_nodes_subset_config.json
renkuaqs/graph_reduction_config.json
renkuaqs/graph_utils.py
renkuaqs/javascript_graph_utils.py
renkuaqs/ontology.ttl
renkuaqs/plugin.py
renkuaqs/icons/graph_icon.svg
renku_aqs-1.0.7.dist-info/LICENSE
renku_aqs-1.0.7.dist-info/METADATA
renku_aqs-1.0.7.dist-info/WHEEL
renku_aqs-1.0.7.dist-info/entry_points.txt
renku_aqs-1.0.7.dist-info/top_level.txt
renku_aqs-1.0.7.dist-info/RECORD
